jupyterlab_conda_store/__init__.py
jupyterlab_conda_store/_version.py
jupyterlab_conda_store/labextension/package.json
jupyterlab_conda_store/labextension/schemas/jupyterlab-conda-store/package.json.orig
jupyterlab_conda_store/labextension/schemas/jupyterlab-conda-store/plugin.json
jupyterlab_conda_store/labextension/static/728.809a45df8b7e3911fd62.js
jupyterlab_conda_store/labextension/static/907.c2903223595841279041.js
jupyterlab_conda_store/labextension/static/938.d469db961aa98d7f8f67.js
jupyterlab_conda_store/labextension/static/938.d469db961aa98d7f8f67.js.LICENSE.txt
jupyterlab_conda_store/labextension/static/remoteEntry.dd61bfcce80ae8720c90.js
jupyterlab_conda_store/labextension/static/style.js
jupyterlab_conda_store/labextension/static/third-party-licenses.json
jupyterlab_conda_store-2024.11.1.data/data/share/jupyter/labextensions/jupyterlab-conda-store/package.json
jupyterlab_conda_store-2024.11.1.data/data/share/jupyter/labextensions/jupyterlab-conda-store/schemas/jupyterlab-conda-store/package.json.orig
jupyterlab_conda_store-2024.11.1.data/data/share/jupyter/labextensions/jupyterlab-conda-store/schemas/jupyterlab-conda-store/plugin.json
jupyterlab_conda_store-2024.11.1.data/data/share/jupyter/labextensions/jupyterlab-conda-store/static/728.809a45df8b7e3911fd62.js
jupyterlab_conda_store-2024.11.1.data/data/share/jupyter/labextensions/jupyterlab-conda-store/static/907.c2903223595841279041.js
jupyterlab_conda_store-2024.11.1.data/data/share/jupyter/labextensions/jupyterlab-conda-store/static/938.d469db961aa98d7f8f67.js
jupyterlab_conda_store-2024.11.1.data/data/share/jupyter/labextensions/jupyterlab-conda-store/static/938.d469db961aa98d7f8f67.js.LICENSE.txt
jupyterlab_conda_store-2024.11.1.data/data/share/jupyter/labextensions/jupyterlab-conda-store/static/remoteEntry.dd61bfcce80ae8720c90.js
jupyterlab_conda_store-2024.11.1.data/data/share/jupyter/labextensions/jupyterlab-conda-store/static/style.js
jupyterlab_conda_store-2024.11.1.dist-info/METADATA
jupyterlab_conda_store-2024.11.1.dist-info/WHEEL
jupyterlab_conda_store-2024.11.1.dist-info/licenses/LICENSE
jupyterlab_conda_store-2024.11.1.dist-info/RECORD
