Metadata-Version: 2.3
Name: jupyterlab-conda-store
Version: 2024.11.1
Summary: A JupyterLab extension that provides a user-friendly graphical interface for building and managing environments using an existing conda-store server
Project-URL: Homepage, https://github.com/conda-incubator/jupyterlab-conda-store
Project-URL: Repository, https://github.com/conda-incubator/jupyterlab-conda-store
Maintainer-email: Tania Allard <trallard@bitsandchips.me>
License: BSD 3-Clause License
Keywords: Jupyter,JupyterLab,JupyterLab4,conda,environments
Classifier: Framework :: Jupyter
Classifier: Framework :: Jupyter :: JupyterLab
Classifier: Framework :: Jupyter :: JupyterLab :: 4
Classifier: Framework :: Jupyter :: JupyterLab :: Extensions
Classifier: Framework :: Jupyter :: JupyterLab :: Extensions :: Prebuilt
Classifier: License :: OSI Approved :: BSD License
Classifier: Programming Language :: Python
Classifier: Programming Language :: Python :: 3
Classifier: Programming Language :: Python :: 3.8
Classifier: Programming Language :: Python :: 3.9
Classifier: Programming Language :: Python :: 3.10
Classifier: Programming Language :: Python :: 3.11
Requires-Python: >=3.9
Provides-Extra: dev
Requires-Dist: hatch; extra == 'dev'
Provides-Extra: test
Requires-Dist: coverage; extra == 'test'
Requires-Dist: pytest; extra == 'test'
Requires-Dist: pytest-asyncio; extra == 'test'
Requires-Dist: pytest-cov; extra == 'test'
Requires-Dist: pytest-tornasync; extra == 'test'
